{
  "minecraft:recipes/redstone/lever": {
    "criteria": {
      "has_cobblestone": "2025-03-31 00:29:29 +0000"
    },
    "done": true
  },
  "minecraft:recipes/combat/leather_helmet": {
    "criteria": {
      "has_leather": "2025-03-31 00:23:41 +0000"
    },
    "done": true
  },
  "slashblade:arts/combo_a": {
    "criteria": {
      "customtrigger": "2025-03-31 00:23:23 +0000"
    },
    "done": true
  },
  "minecraft:recipes/decorations/ladder": {
    "criteria": {
      "has_stick": "2025-03-31 00:17:58 +0000"
    },
    "done": true
  },
  "slashblade:arts/combo_c": {
    "criteria": {
      "customtrigger": "2025-03-31 00:24:49 +0000"
    },
    "done": true
  },
  "minecraft:recipes/combat/iron_leggings": {
    "criteria": {
      "has_iron_ingot": "2025-03-31 00:20:47 +0000"
    },
    "done": true
  },
  "minecraft:recipes/building_blocks/light_gray_concrete_powder": {
    "criteria": {
      "has_sand": "2025-03-31 00:16:30 +0000"
    },
    "done": true
  },
  "minecraft:recipes/combat/leather_leggings": {
    "criteria": {
      "has_leather": "2025-03-31 00:23:41 +0000"
    },
    "done": true
  },
  "minecraft:recipes/building_blocks/pink_concrete_powder": {
    "criteria": {
      "has_sand": "2025-03-31 00:16:30 +0000"
    },
    "done": true
  },
  "toughasnails:recipes/tools/empty_leather_canteen": {
    "criteria": {
      "has_leather": "2025-03-31 00:23:41 +0000"
    },
    "done": true
  },
  "slashblade:movesets": {
    "criteria": {
      "crafting": "2025-03-31 00:12:37 +0000"
    },
    "done": true
  },
  "scguns:main/copper_blueprint": {
    "criteria": {
      "copper_blueprint": "2025-03-31 00:27:32 +0000"
    },
    "done": true
  },
  "minecraft:recipes/misc/iron_nugget_from_smelting": {
    "criteria": {
      "has_iron_pickaxe": "2025-03-31 00:22:14 +0000"
    },
    "done": true
  },
  "minecraft:recipes/food/cooked_mutton_from_smoking": {
    "criteria": {
      "has_mutton": "2025-03-31 00:23:50 +0000"
    },
    "done": true
  },
  "minecraft:recipes/building_blocks/light_blue_stained_glass": {
    "criteria": {
      "has_glass": "2025-03-31 00:30:54 +0000"
    },
    "done": true
  },
  "scguns:main/ocean_blueprint": {
    "criteria": {
      "ocean_blueprint": "2025-03-31 00:20:59 +0000"
    },
    "done": true
  },
  "nova_structures:adventure/find_all_illager_structures": {
    "criteria": {
      "illager_camp": "2025-03-31 00:25:20 +0000"
    },
    "done": false
  },
  "minecraft:recipes/building_blocks/green_stained_glass": {
    "criteria": {
      "has_glass": "2025-03-31 00:30:54 +0000"
    },
    "done": true
  },
  "minecraft:recipes/tools/golden_axe": {
    "criteria": {
      "has_gold_ingot": "2025-03-31 00:20:48 +0000"
    },
    "done": true
  },
  "minecraft:story/iron_tools": {
    "criteria": {
      "iron_pickaxe": "2025-03-31 00:22:14 +0000"
    },
    "done": true
  },
  "minecraft:recipes/combat/iron_chestplate": {
    "criteria": {
      "has_iron_ingot": "2025-03-31 00:20:47 +0000"
    },
    "done": true
  },
  "minecraft:recipes/decorations/oak_sign": {
    "criteria": {
      "has_planks": "2025-03-31 00:17:44 +0000"
    },
    "done": true
  },
  "minecraft:recipes/redstone/oak_trapdoor": {
    "criteria": {
      "has_planks": "2025-03-31 00:17:44 +0000"
    },
    "done": true
  },
  "minecraft:recipes/building_blocks/red_concrete_powder": {
    "criteria": {
      "has_sand": "2025-03-31 00:16:30 +0000"
    },
    "done": true
  },
  "minecraft:recipes/tools/golden_pickaxe": {
    "criteria": {
      "has_gold_ingot": "2025-03-31 00:20:48 +0000"
    },
    "done": true
  },
  "slashblade:material/proudsoul_tiny": {
    "criteria": {
      "BrokenBlade": "2025-03-31 00:23:18 +0000"
    },
    "done": true
  },
  "minecraft:recipes/combat/stone_sword": {
    "criteria": {
      "has_cobblestone": "2025-03-31 00:29:29 +0000"
    },
    "done": true
  },
  "minecraft:recipes/decorations/cobblestone_wall": {
    "criteria": {
      "has_cobblestone": "2025-03-31 00:29:29 +0000"
    },
    "done": true
  },
  "minecraft:recipes/building_blocks/brown_stained_glass": {
    "criteria": {
      "has_glass": "2025-03-31 00:30:54 +0000"
    },
    "done": true
  },
  "minecraft:recipes/tools/stone_axe": {
    "criteria": {
      "has_cobblestone": "2025-03-31 00:29:29 +0000"
    },
    "done": true
  },
  "minecraft:recipes/building_blocks/raw_iron_block": {
    "criteria": {
      "has_raw_iron": "2025-03-31 00:34:02 +0000"
    },
    "done": true
  },
  "toughasnails:recipes/tools/empty_iron_canteen": {
    "criteria": {
      "has_iron_ingot": "2025-03-31 00:20:47 +0000"
    },
    "done": true
  },
  "minecraft:recipes/misc/iron_nugget": {
    "criteria": {
      "has_iron_ingot": "2025-03-31 00:20:47 +0000"
    },
    "done": true
  },
  "minecraft:recipes/building_blocks/brown_concrete_powder": {
    "criteria": {
      "has_sand": "2025-03-31 00:16:30 +0000"
    },
    "done": true
  },
  "minecraft:recipes/building_blocks/blue_stained_glass": {
    "criteria": {
      "has_glass": "2025-03-31 00:30:54 +0000"
    },
    "done": true
  },
  "minecraft:recipes/misc/gold_nugget": {
    "criteria": {
      "has_gold_ingot": "2025-03-31 00:20:48 +0000"
    },
    "done": true
  },
  "minecraft:recipes/misc/bucket": {
    "criteria": {
      "has_iron_ingot": "2025-03-31 00:20:47 +0000"
    },
    "done": true
  },
  "minecraft:recipes/building_blocks/light_blue_concrete_powder": {
    "criteria": {
      "has_sand": "2025-03-31 00:16:30 +0000"
    },
    "done": true
  },
  "minecraft:recipes/building_blocks/glass": {
    "criteria": {
      "has_smelts_to_glass": "2025-03-31 00:16:30 +0000"
    },
    "done": true
  },
  "minecraft:recipes/combat/iron_helmet": {
    "criteria": {
      "has_iron_ingot": "2025-03-31 00:20:47 +0000"
    },
    "done": true
  },
  "minecraft:recipes/tools/golden_shovel": {
    "criteria": {
      "has_gold_ingot": "2025-03-31 00:20:48 +0000"
    },
    "done": true
  },
  "minecraft:story/mine_stone": {
    "criteria": {
      "get_stone": "2025-03-31 00:29:29 +0000"
    },
    "done": true
  },
  "minecraft:recipes/decorations/furnace": {
    "criteria": {
      "has_cobblestone": "2025-03-31 00:29:29 +0000"
    },
    "done": true
  },
  "minecraft:recipes/transportation/minecart": {
    "criteria": {
      "has_iron_ingot": "2025-03-31 00:20:47 +0000"
    },
    "done": true
  },
  "minecraft:recipes/tools/iron_hoe": {
    "criteria": {
      "has_iron_ingot": "2025-03-31 00:20:47 +0000"
    },
    "done": true
  },
  "slashblade:material/proudsoul": {
    "criteria": {
      "BrokenBlade": "2025-03-31 00:24:37 +0000"
    },
    "done": true
  },
  "minecraft:recipes/food/golden_apple": {
    "criteria": {
      "has_gold_ingot": "2025-03-31 00:20:48 +0000"
    },
    "done": true
  },
  "minecraft:recipes/building_blocks/green_concrete_powder": {
    "criteria": {
      "has_sand": "2025-03-31 00:16:30 +0000"
    },
    "done": true
  },
  "minecraft:recipes/building_blocks/orange_stained_glass": {
    "criteria": {
      "has_glass": "2025-03-31 00:30:54 +0000"
    },
    "done": true
  },
  "minecraft:recipes/combat/golden_boots": {
    "criteria": {
      "has_gold_ingot": "2025-03-31 00:20:48 +0000"
    },
    "done": true
  },
  "minecraft:recipes/tools/wooden_axe": {
    "criteria": {
      "has_stick": "2025-03-31 00:17:58 +0000"
    },
    "done": true
  },
  "minecraft:recipes/decorations/spruce_sign": {
    "criteria": {
      "has_planks": "2025-03-31 00:18:34 +0000"
    },
    "done": true
  },
  "minecraft:recipes/decorations/painting": {
    "criteria": {
      "has_wool": "2025-03-31 00:23:50 +0000"
    },
    "done": true
  },
  "minecraft:recipes/building_blocks/blue_concrete_powder": {
    "criteria": {
      "has_sand": "2025-03-31 00:16:30 +0000"
    },
    "done": true
  },
  "minecraft:recipes/combat/golden_helmet": {
    "criteria": {
      "has_gold_ingot": "2025-03-31 00:20:48 +0000"
    },
    "done": true
  },
  "minecraft:recipes/combat/leather_chestplate": {
    "criteria": {
      "has_leather": "2025-03-31 00:23:41 +0000"
    },
    "done": true
  },
  "minecraft:recipes/decorations/composter": {
    "criteria": {
      "has_wood_slab": "2025-03-31 00:17:03 +0000"
    },
    "done": true
  },
  "immersive_aircraft:misc/aircraftery": {
    "criteria": {
      "has_item": "2025-03-31 00:20:47 +0000"
    },
    "done": true
  },
  "minecraft:story/smelt_iron": {
    "criteria": {
      "iron": "2025-03-31 00:20:47 +0000"
    },
    "done": true
  },
  "minecraft:recipes/building_blocks/pink_stained_glass": {
    "criteria": {
      "has_glass": "2025-03-31 00:30:54 +0000"
    },
    "done": true
  },
  "minecraft:recipes/decorations/smoker": {
    "criteria": {
      "has_furnace": "2025-03-31 00:29:59 +0000"
    },
    "done": true
  },
  "minecraft:recipes/building_blocks/black_stained_glass": {
    "criteria": {
      "has_glass": "2025-03-31 00:30:54 +0000"
    },
    "done": true
  },
  "minecraft:recipes/building_blocks/gray_stained_glass": {
    "criteria": {
      "has_glass": "2025-03-31 00:30:54 +0000"
    },
    "done": true
  },
  "minecraft:recipes/decorations/crafting_table": {
    "criteria": {
      "unlock_right_away": "2025-03-31 00:11:45 +0000"
    },
    "done": true
  },
  "minecraft:recipes/decorations/chest": {
    "criteria": {
      "has_lots_of_items": "2025-03-31 00:18:48 +0000"
    },
    "done": true
  },
  "minecraft:recipes/tools/shears": {
    "criteria": {
      "has_iron_ingot": "2025-03-31 00:20:47 +0000"
    },
    "done": true
  },
  "minecraft:recipes/misc/stick": {
    "criteria": {
      "has_planks": "2025-03-31 00:17:44 +0000"
    },
    "done": true
  },
  "minecraft:recipes/building_blocks/emerald_block": {
    "criteria": {
      "has_emerald": "2025-03-31 00:20:51 +0000"
    },
    "done": true
  },
  "slashblade:abilities/enemy_step": {
    "criteria": {
      "customtrigger": "2025-03-31 00:24:46 +0000"
    },
    "done": true
  },
  "minecraft:adventure/sleep_in_bed": {
    "criteria": {
      "slept_in_bed": "2025-03-31 00:26:13 +0000"
    },
    "done": true
  },
  "minecraft:recipes/building_blocks/cobblestone_slab_from_cobblestone_stonecutting": {
    "criteria": {
      "has_cobblestone": "2025-03-31 00:29:29 +0000"
    },
    "done": true
  },
  "minecraft:recipes/building_blocks/oak_stairs": {
    "criteria": {
      "has_planks": "2025-03-31 00:17:44 +0000"
    },
    "done": true
  },
  "minecraft:recipes/building_blocks/white_concrete_powder": {
    "criteria": {
      "has_sand": "2025-03-31 00:16:30 +0000"
    },
    "done": true
  },
  "scguns:main/gunpowder": {
    "criteria": {
      "gunpowder": "2025-03-31 00:23:25 +0000"
    },
    "done": true
  },
  "minecraft:adventure/kill_all_mobs": {
    "criteria": {
      "minecraft:pillager": "2025-03-31 00:24:49 +0000",
      "minecraft:skeleton": "2025-03-31 00:23:30 +0000",
      "minecraft:spider": "2025-03-31 00:25:30 +0000",
      "minecraft:creeper": "2025-03-31 00:23:24 +0000",
      "minecraft:zombie": "2025-03-31 00:24:38 +0000"
    },
    "done": false
  },
  "minecraft:recipes/building_blocks/lime_stained_glass": {
    "criteria": {
      "has_glass": "2025-03-31 00:30:54 +0000"
    },
    "done": true
  },
  "minecraft:recipes/decorations/chain": {
    "criteria": {
      "has_iron_ingot": "2025-03-31 00:20:47 +0000"
    },
    "done": true
  },
  "minecraft:recipes/decorations/oak_fence": {
    "criteria": {
      "has_planks": "2025-03-31 00:17:44 +0000"
    },
    "done": true
  },
  "minecraft:recipes/combat/golden_chestplate": {
    "criteria": {
      "has_gold_ingot": "2025-03-31 00:20:48 +0000"
    },
    "done": true
  },
  "minecraft:recipes/building_blocks/iron_block": {
    "criteria": {
      "has_iron_ingot": "2025-03-31 00:20:47 +0000"
    },
    "done": true
  },
  "mowziesmobs:root": {
    "criteria": {
      "custom_test_name": "2025-03-31 00:11:45 +0000"
    },
    "done": true
  },
  "craftkaiju:craft_kaiju_begginings": {
    "criteria": {
      "craft_kaiju_begginings": "2025-03-31 00:11:45 +0000"
    },
    "done": true
  },
  "toughasnails:recipes/food/apple_juice": {
    "criteria": {
      "has_apple": "2025-03-31 00:25:41 +0000"
    },
    "done": true
  },
  "minecraft:recipes/building_blocks/stone": {
    "criteria": {
      "has_cobblestone": "2025-03-31 00:29:29 +0000"
    },
    "done": true
  },
  "minecraft:recipes/decorations/smithing_table": {
    "criteria": {
      "has_iron_ingot": "2025-03-31 00:20:47 +0000"
    },
    "done": true
  },
  "eeeabsmobs:eeeabsmobs/root": {
    "criteria": {
      "requirement": "2025-03-31 00:11:45 +0000"
    },
    "done": true
  },
  "minecraft:recipes/redstone/jungle_button": {
    "criteria": {
      "has_planks": "2025-03-31 00:18:34 +0000"
    },
    "done": true
  },
  "minecraft:recipes/misc/leather_horse_armor": {
    "criteria": {
      "has_leather": "2025-03-31 00:23:41 +0000"
    },
    "done": true
  },
  "minecraft:husbandry/root": {
    "criteria": {
      "consumed_item": "2025-03-31 00:24:37 +0000"
    },
    "done": true
  },
  "slashblade:recipes/combat/yuzukitukumo": {
    "criteria": {
      "has_slashblade": "2025-03-31 00:13:49 +0000"
    },
    "done": true
  },
  "toughasnails:recipes/combat/wool_helmet": {
    "criteria": {
      "has_wool": "2025-03-31 00:23:50 +0000"
    },
    "done": true
  },
  "minecraft:recipes/decorations/spruce_fence": {
    "criteria": {
      "has_planks": "2025-03-31 00:18:34 +0000"
    },
    "done": true
  },
  "slashblade:arts/aerial_b": {
    "criteria": {
      "customtrigger": "2025-03-31 00:23:35 +0000"
    },
    "done": true
  },
  "slashblade:arts/aerial_a": {
    "criteria": {
      "customtrigger": "2025-03-31 00:16:11 +0000"
    },
    "done": true
  },
  "minecraft:recipes/decorations/white_carpet": {
    "criteria": {
      "has_white_wool": "2025-03-31 00:23:53 +0000"
    },
    "done": true
  },
  "minecraft:recipes/decorations/glass_pane": {
    "criteria": {
      "has_glass": "2025-03-31 00:30:54 +0000"
    },
    "done": true
  },
  "minecraft:recipes/building_blocks/magenta_stained_glass": {
    "criteria": {
      "has_glass": "2025-03-31 00:30:54 +0000"
    },
    "done": true
  },
  "minecraft:recipes/building_blocks/white_stained_glass": {
    "criteria": {
      "has_glass": "2025-03-31 00:30:54 +0000"
    },
    "done": true
  },
  "minecraft:recipes/building_blocks/coal_block": {
    "criteria": {
      "has_coal": "2025-03-31 00:32:32 +0000"
    },
    "done": true
  },
  "minecraft:recipes/redstone/light_weighted_pressure_plate": {
    "criteria": {
      "has_gold_ingot": "2025-03-31 00:20:48 +0000"
    },
    "done": true
  },
  "minecraft:recipes/misc/conduit": {
    "criteria": {
      "has_nautilus_core": "2025-03-31 00:21:14 +0000"
    },
    "done": true
  },
  "minecraft:recipes/building_blocks/spruce_slab": {
    "criteria": {
      "has_planks": "2025-03-31 00:18:34 +0000"
    },
    "done": true
  },
  "cataclysm:root": {
    "criteria": {
      "custom_test_name": "2025-03-31 00:11:45 +0000"
    },
    "done": true
  },
  "slashblade:root": {
    "criteria": {
      "attackTheEntity": "2025-03-31 00:23:18 +0000"
    },
    "done": true
  },
  "twilightforest:recipes/decorations/wood/jungle_banister": {
    "criteria": {
      "has_item": "2025-03-31 00:17:03 +0000"
    },
    "done": true
  },
  "minecraft:recipes/redstone/oak_button": {
    "criteria": {
      "has_planks": "2025-03-31 00:17:44 +0000"
    },
    "done": true
  },
  "globalxp:recipes/misc/xp_block": {
    "criteria": {
      "has_emerald": "2025-03-31 00:20:51 +0000"
    },
    "done": true
  },
  "incendium:technical/new_player": {
    "criteria": {
      "requirement": "2025-03-31 00:11:45 +0000"
    },
    "done": true
  },
  "minecraft:recipes/building_blocks/jungle_stairs": {
    "criteria": {
      "has_planks": "2025-03-31 00:18:34 +0000"
    },
    "done": true
  },
  "minecraft:recipes/redstone/jungle_fence_gate": {
    "criteria": {
      "has_planks": "2025-03-31 00:18:34 +0000"
    },
    "done": true
  },
  "minecraft:recipes/combat/iron_sword": {
    "criteria": {
      "has_iron_ingot": "2025-03-31 00:20:47 +0000"
    },
    "done": true
  },
  "minecraft:recipes/building_blocks/lime_concrete_powder": {
    "criteria": {
      "has_sand": "2025-03-31 00:16:30 +0000"
    },
    "done": true
  },
  "minecraft:recipes/tools/iron_pickaxe": {
    "criteria": {
      "has_iron_ingot": "2025-03-31 00:20:47 +0000"
    },
    "done": true
  },
  "minecraft:recipes/redstone/spruce_button": {
    "criteria": {
      "has_planks": "2025-03-31 00:18:34 +0000"
    },
    "done": true
  },
  "minecraft:recipes/decorations/torch": {
    "criteria": {
      "has_the_recipe": "2025-03-31 00:33:29 +0000"
    },
    "done": true
  },
  "minecraft:recipes/combat/shield": {
    "criteria": {
      "has_iron_ingot": "2025-03-31 00:20:47 +0000"
    },
    "done": true
  },
  "minecraft:recipes/redstone/hopper": {
    "criteria": {
      "has_iron_ingot": "2025-03-31 00:20:47 +0000"
    },
    "done": true
  },
  "minecraft:recipes/decorations/iron_bars": {
    "criteria": {
      "has_iron_ingot": "2025-03-31 00:20:47 +0000"
    },
    "done": true
  },
  "incendium:technical/scroll_of_returning": {
    "criteria": {
      "log_spam_fixer": "2025-03-31 00:11:46 +0000"
    },
    "done": false
  },
  "slashblade:recipes/combat/muramasa": {
    "criteria": {
      "has_slashblade": "2025-03-31 00:13:49 +0000"
    },
    "done": true
  },
  "minecraft:recipes/building_blocks/red_stained_glass": {
    "criteria": {
      "has_glass": "2025-03-31 00:30:54 +0000"
    },
    "done": true
  },
  "sophisticatedbackpacks:recipes/misc/backpack": {
    "criteria": {
      "has_leather": "2025-03-31 00:23:41 +0000"
    },
    "done": true
  },
  "minecraft:recipes/food/cooked_beef_from_smoking": {
    "criteria": {
      "has_beef": "2025-03-31 00:23:42 +0000"
    },
    "done": true
  },
  "minecraft:recipes/building_blocks/orange_concrete_powder": {
    "criteria": {
      "has_sand": "2025-03-31 00:16:30 +0000"
    },
    "done": true
  },
  "minecraft:recipes/building_blocks/oak_slab": {
    "criteria": {
      "has_planks": "2025-03-31 00:17:44 +0000"
    },
    "done": true
  },
  "minecraft:recipes/brewing/glass_bottle": {
    "criteria": {
      "has_glass": "2025-03-31 00:30:54 +0000"
    },
    "done": true
  },
  "minecraft:recipes/decorations/light_gray_bed": {
    "criteria": {
      "has_light_gray_wool": "2025-03-31 00:23:50 +0000"
    },
    "done": true
  },
  "toughasnails:recipes/tools/empty_gold_canteen": {
    "criteria": {
      "has_gold_ingot": "2025-03-31 00:20:48 +0000"
    },
    "done": true
  },
  "minecraft:recipes/combat/iron_boots": {
    "criteria": {
      "has_iron_ingot": "2025-03-31 00:20:47 +0000"
    },
    "done": true
  },
  "minecraft:recipes/redstone/spruce_pressure_plate": {
    "criteria": {
      "has_planks": "2025-03-31 00:18:34 +0000"
    },
    "done": true
  },
  "toughasnails:recipes/combat/wool_boots": {
    "criteria": {
      "has_wool": "2025-03-31 00:23:50 +0000"
    },
    "done": true
  },
  "incendium:technical/using/ragnarok": {
    "criteria": {
      "log_spam_fixer": "2025-03-31 00:11:46 +0000"
    },
    "done": false
  },
  "minecraft:recipes/misc/iron_ingot_from_smelting_raw_iron": {
    "criteria": {
      "has_raw_iron": "2025-03-31 00:34:02 +0000"
    },
    "done": true
  },
  "minecraft:recipes/tools/stone_pickaxe": {
    "criteria": {
      "has_cobblestone": "2025-03-31 00:29:29 +0000"
    },
    "done": true
  },
  "minecraft:recipes/building_blocks/light_gray_stained_glass": {
    "criteria": {
      "has_glass": "2025-03-31 00:30:54 +0000"
    },
    "done": true
  },
  "dungeons_arise:wda_root": {
    "criteria": {
      "WDA": "2025-03-31 00:11:45 +0000"
    },
    "done": true
  },
  "minecraft:recipes/decorations/lantern": {
    "criteria": {
      "has_iron_ingot": "2025-03-31 00:20:47 +0000"
    },
    "done": true
  },
  "minecraft:recipes/food/cooked_mutton": {
    "criteria": {
      "has_mutton": "2025-03-31 00:23:50 +0000"
    },
    "done": true
  },
  "minecraft:recipes/building_blocks/magenta_concrete_powder": {
    "criteria": {
      "has_sand": "2025-03-31 00:16:30 +0000"
    },
    "done": true
  },
  "minecraft:recipes/decorations/campfire": {
    "criteria": {
      "has_stick": "2025-03-31 00:17:58 +0000"
    },
    "done": true
  },
  "minecraft:recipes/redstone/jungle_trapdoor": {
    "criteria": {
      "has_planks": "2025-03-31 00:18:34 +0000"
    },
    "done": true
  },
  "minecraft:recipes/tools/wooden_hoe": {
    "criteria": {
      "has_stick": "2025-03-31 00:17:58 +0000"
    },
    "done": true
  },
  "minecraft:recipes/decorations/white_banner": {
    "criteria": {
      "has_white_wool": "2025-03-31 00:23:53 +0000"
    },
    "done": true
  },
  "minecraft:recipes/redstone/oak_fence_gate": {
    "criteria": {
      "has_planks": "2025-03-31 00:17:44 +0000"
    },
    "done": true
  },
  "minecraft:recipes/misc/charcoal": {
    "criteria": {
      "has_log": "2025-03-31 00:17:22 +0000"
    },
    "done": true
  },
  "minecraft:recipes/tools/wooden_pickaxe": {
    "criteria": {
      "has_stick": "2025-03-31 00:17:58 +0000"
    },
    "done": true
  },
  "minecraft:recipes/tools/iron_shovel": {
    "criteria": {
      "has_iron_ingot": "2025-03-31 00:20:47 +0000"
    },
    "done": true
  },
  "minecraft:recipes/decorations/item_frame": {
    "criteria": {
      "has_leather": "2025-03-31 00:23:41 +0000"
    },
    "done": true
  },
  "scguns:main/root": {
    "criteria": {
      "gun": "2025-03-31 00:12:37 +0000"
    },
    "done": true
  },
  "slashblade:arts/quick_charge": {
    "criteria": {
      "customtrigger": "2025-03-31 00:23:21 +0000"
    },
    "done": true
  },
  "minecraft:recipes/building_blocks/cyan_stained_glass": {
    "criteria": {
      "has_glass": "2025-03-31 00:30:54 +0000"
    },
    "done": true
  },
  "minecraft:recipes/decorations/jungle_sign": {
    "criteria": {
      "has_planks": "2025-03-31 00:18:34 +0000"
    },
    "done": true
  },
  "sophisticatedbackpacks:recipes/misc/upgrade_base": {
    "criteria": {
      "has_leather": "2025-03-31 00:23:41 +0000"
    },
    "done": true
  },
  "minecraft:recipes/redstone/oak_pressure_plate": {
    "criteria": {
      "has_planks": "2025-03-31 00:17:44 +0000"
    },
    "done": true
  },
  "minecraft:recipes/redstone/oak_door": {
    "criteria": {
      "has_planks": "2025-03-31 00:17:44 +0000"
    },
    "done": true
  },
  "minecraft:recipes/redstone/jungle_door": {
    "criteria": {
      "has_planks": "2025-03-31 00:18:34 +0000"
    },
    "done": true
  },
  "minecraft:recipes/redstone/spruce_trapdoor": {
    "criteria": {
      "has_planks": "2025-03-31 00:18:34 +0000"
    },
    "done": true
  },
  "man_of_many_planes:misc/expanded_aircraftery": {
    "criteria": {
      "has_item": "2025-03-31 00:20:47 +0000"
    },
    "done": true
  },
  "minecraft:recipes/food/cooked_mutton_from_campfire_cooking": {
    "criteria": {
      "has_mutton": "2025-03-31 00:23:50 +0000"
    },
    "done": true
  },
  "minecraft:recipes/redstone/spruce_door": {
    "criteria": {
      "has_planks": "2025-03-31 00:18:34 +0000"
    },
    "done": true
  },
  "minecraft:recipes/building_blocks/yellow_concrete_powder": {
    "criteria": {
      "has_sand": "2025-03-31 00:16:30 +0000"
    },
    "done": true
  },
  "minecraft:recipes/redstone/spruce_fence_gate": {
    "criteria": {
      "has_planks": "2025-03-31 00:18:34 +0000"
    },
    "done": true
  },
  "minecraft:recipes/building_blocks/purple_stained_glass": {
    "criteria": {
      "has_glass": "2025-03-31 00:30:54 +0000"
    },
    "done": true
  },
  "minecraft:recipes/combat/golden_sword": {
    "criteria": {
      "has_gold_ingot": "2025-03-31 00:20:48 +0000"
    },
    "done": true
  },
  "minecraft:recipes/tools/wooden_shovel": {
    "criteria": {
      "has_stick": "2025-03-31 00:17:58 +0000"
    },
    "done": true
  },
  "minecraft:recipes/building_blocks/cobblestone_slab": {
    "criteria": {
      "has_cobblestone": "2025-03-31 00:29:29 +0000"
    },
    "done": true
  },
  "incendium:technical/using/trailblazer": {
    "criteria": {
      "log_spam_fixer": "2025-03-31 00:11:46 +0000"
    },
    "done": false
  },
  "minecraft:recipes/building_blocks/yellow_stained_glass": {
    "criteria": {
      "has_glass": "2025-03-31 00:30:54 +0000"
    },
    "done": true
  },
  "minecraft:recipes/building_blocks/gold_block": {
    "criteria": {
      "has_gold_ingot": "2025-03-31 00:20:48 +0000"
    },
    "done": true
  },
  "minecraft:recipes/building_blocks/sandstone": {
    "criteria": {
      "has_sand": "2025-03-31 00:16:30 +0000"
    },
    "done": true
  },
  "minecraft:recipes/redstone/iron_trapdoor": {
    "criteria": {
      "has_iron_ingot": "2025-03-31 00:20:47 +0000"
    },
    "done": true
  },
  "minecraft:adventure/root": {
    "criteria": {
      "killed_something": "2025-03-31 00:23:24 +0000"
    },
    "done": true
  },
  "minecraft:recipes/decorations/jungle_fence": {
    "criteria": {
      "has_planks": "2025-03-31 00:18:34 +0000"
    },
    "done": true
  },
  "minecraft:recipes/redstone/jungle_pressure_plate": {
    "criteria": {
      "has_planks": "2025-03-31 00:18:34 +0000"
    },
    "done": true
  },
  "minecraft:recipes/misc/iron_ingot_from_blasting_raw_iron": {
    "criteria": {
      "has_raw_iron": "2025-03-31 00:34:02 +0000"
    },
    "done": true
  },
  "minecraft:recipes/combat/wooden_sword": {
    "criteria": {
      "has_stick": "2025-03-31 00:17:58 +0000"
    },
    "done": true
  },
  "minecraft:recipes/building_blocks/oak_planks": {
    "criteria": {
      "has_logs": "2025-03-31 00:17:22 +0000"
    },
    "done": true
  },
  "minecraft:recipes/building_blocks/gray_concrete_powder": {
    "criteria": {
      "has_sand": "2025-03-31 00:16:30 +0000"
    },
    "done": true
  },
  "minecraft:recipes/decorations/light_gray_banner": {
    "criteria": {
      "has_light_gray_wool": "2025-03-31 00:23:50 +0000"
    },
    "done": true
  },
  "minecraft:recipes/tools/iron_axe": {
    "criteria": {
      "has_iron_ingot": "2025-03-31 00:20:47 +0000"
    },
    "done": true
  },
  "minecraft:recipes/building_blocks/black_concrete_powder": {
    "criteria": {
      "has_sand": "2025-03-31 00:16:30 +0000"
    },
    "done": true
  },
  "minecraft:recipes/combat/crossbow": {
    "criteria": {
      "has_iron_ingot": "2025-03-31 00:20:47 +0000"
    },
    "done": true
  },
  "minecraft:recipes/misc/iron_nugget_from_blasting": {
    "criteria": {
      "has_iron_pickaxe": "2025-03-31 00:22:14 +0000"
    },
    "done": true
  },
  "minecraft:adventure/kill_a_mob": {
    "criteria": {
      "minecraft:creeper": "2025-03-31 00:23:24 +0000"
    },
    "done": true
  },
  "sophisticatedbackpacks:recipes/misc/gold_backpack": {
    "criteria": {
      "has_iron_backpack": "2025-03-31 00:12:37 +0000"
    },
    "done": true
  },
  "minecraft:adventure/adventuring_time": {
    "criteria": {
      "minecraft:beach": "2025-03-31 00:11:46 +0000",
      "minecraft:lukewarm_ocean": "2025-03-31 00:11:56 +0000",
      "minecraft:swamp": "2025-03-31 00:17:17 +0000",
      "minecraft:plains": "2025-03-31 00:16:03 +0000"
    },
    "done": false
  },
  "minecraft:recipes/decorations/light_gray_carpet": {
    "criteria": {
      "has_light_gray_wool": "2025-03-31 00:23:50 +0000"
    },
    "done": true
  },
  "minecraft:recipes/decorations/barrel": {
    "criteria": {
      "has_wood_slab": "2025-03-31 00:17:03 +0000"
    },
    "done": true
  },
  "minecraft:recipes/combat/leather_boots": {
    "criteria": {
      "has_leather": "2025-03-31 00:23:41 +0000"
    },
    "done": true
  },
  "minecraft:recipes/decorations/cobblestone_wall_from_cobblestone_stonecutting": {
    "criteria": {
      "has_cobblestone": "2025-03-31 00:29:29 +0000"
    },
    "done": true
  },
  "celestisynth:recipes/decorations/starlit_factory_update_fix": {
    "criteria": {
      "has_item": "2025-03-31 00:17:53 +0000"
    },
    "done": true
  },
  "slashblade:abilities/kick_jump": {
    "criteria": {
      "customtrigger": "2025-03-31 00:16:18 +0000"
    },
    "done": true
  },
  "minecraft:recipes/building_blocks/cobblestone_stairs_from_cobblestone_stonecutting": {
    "criteria": {
      "has_cobblestone": "2025-03-31 00:29:29 +0000"
    },
    "done": true
  },
  "minecraft:recipes/decorations/white_bed": {
    "criteria": {
      "has_white_wool": "2025-03-31 00:23:53 +0000"
    },
    "done": true
  },
  "minecraft:recipes/tools/golden_hoe": {
    "criteria": {
      "has_gold_ingot": "2025-03-31 00:20:48 +0000"
    },
    "done": true
  },
  "minecraft:recipes/misc/firework_rocket_simple": {
    "criteria": {
      "has_gunpowder": "2025-03-31 00:23:25 +0000"
    },
    "done": true
  },
  "minecraft:husbandry/balanced_diet": {
    "criteria": {
      "cooked_cod": "2025-03-31 00:24:37 +0000"
    },
    "done": false
  },
  "minecraft:recipes/building_blocks/cobblestone_stairs": {
    "criteria": {
      "has_cobblestone": "2025-03-31 00:29:29 +0000"
    },
    "done": true
  },
  "incendium:technical/using/shield": {
    "criteria": {
      "log_spam_fixer": "2025-03-31 00:11:46 +0000"
    },
    "done": false
  },
  "minecraft:recipes/redstone/tnt": {
    "criteria": {
      "has_gunpowder": "2025-03-31 00:23:25 +0000"
    },
    "done": true
  },
  "minecraft:recipes/building_blocks/purple_concrete_powder": {
    "criteria": {
      "has_sand": "2025-03-31 00:16:30 +0000"
    },
    "done": true
  },
  "minecraft:recipes/tools/stone_hoe": {
    "criteria": {
      "has_cobblestone": "2025-03-31 00:29:29 +0000"
    },
    "done": true
  },
  "minecraft:recipes/building_blocks/spruce_stairs": {
    "criteria": {
      "has_planks": "2025-03-31 00:18:34 +0000"
    },
    "done": true
  },
  "minecraft:recipes/building_blocks/cyan_concrete_powder": {
    "criteria": {
      "has_sand": "2025-03-31 00:16:30 +0000"
    },
    "done": true
  },
  "minecraft:recipes/tools/stone_shovel": {
    "criteria": {
      "has_cobblestone": "2025-03-31 00:29:29 +0000"
    },
    "done": true
  },
  "minecraft:recipes/building_blocks/oak_wood": {
    "criteria": {
      "has_log": "2025-03-31 00:17:22 +0000"
    },
    "done": true
  },
  "minecraft:story/root": {
    "criteria": {
      "crafting_table": "2025-03-31 00:17:53 +0000"
    },
    "done": true
  },
  "toughasnails:recipes/combat/wool_leggings": {
    "criteria": {
      "has_wool": "2025-03-31 00:23:50 +0000"
    },
    "done": true
  },
  "minecraft:recipes/building_blocks/jungle_slab": {
    "criteria": {
      "has_planks": "2025-03-31 00:18:34 +0000"
    },
    "done": true
  },
  "toughasnails:recipes/combat/wool_chestplate": {
    "criteria": {
      "has_wool": "2025-03-31 00:23:50 +0000"
    },
    "done": true
  },
  "minecraft:recipes/food/cooked_beef": {
    "criteria": {
      "has_beef": "2025-03-31 00:23:42 +0000"
    },
    "done": true
  },
  "minecraft:recipes/redstone/iron_door": {
    "criteria": {
      "has_iron_ingot": "2025-03-31 00:20:47 +0000"
    },
    "done": true
  },
  "minecraft:recipes/redstone/heavy_weighted_pressure_plate": {
    "criteria": {
      "has_iron_ingot": "2025-03-31 00:20:47 +0000"
    },
    "done": true
  },
  "minecraft:recipes/combat/golden_leggings": {
    "criteria": {
      "has_gold_ingot": "2025-03-31 00:20:48 +0000"
    },
    "done": true
  },
  "minecraft:recipes/food/cooked_beef_from_campfire_cooking": {
    "criteria": {
      "has_beef": "2025-03-31 00:23:42 +0000"
    },
    "done": true
  },
  "DataVersion": 3465
}